src/__init__.py
src/arffparse.py
arffparse-0.5.dist-info/LICENSE.txt
arffparse-0.5.dist-info/METADATA
arffparse-0.5.dist-info/WHEEL
arffparse-0.5.dist-info/entry_points.txt
arffparse-0.5.dist-info/top_level.txt
arffparse-0.5.dist-info/RECORD
