Metadata-Version: 2.1
Name: arffparse
Version: 0.5
Summary: Small ARFF parsing tool for datasets
Home-page: https://github.com/connormullett/ArffParse
Author: arff parse
Author-email: connormullett@gmail.com
License: MIT
Platform: UNKNOWN
